setup.py
cassandra_migrator.egg-info/PKG-INFO
cassandra_migrator.egg-info/SOURCES.txt
cassandra_migrator.egg-info/dependency_links.txt
cassandra_migrator.egg-info/not-zip-safe
cassandra_migrator.egg-info/requires.txt
cassandra_migrator.egg-info/top_level.txt
migrator/__init__.py
scripts/cmig