Metadata-Version: 1.0
Name: cassandra-migrator
Version: 0.1.4
Summary: cassanra migration tools
Home-page: https://github.com/webscal3r/cassandra-migrator.git
Author: Pitsanu Swangpheaw
Author-email: pitsanu_s@hotmail.com
License: MIT
Platform: UNKNOWN
